{
  "formatVersion": 1,
  "database": {
    "version": 6,
    "identityHash": "633f69f1d2070981b77055c034388dcf",
    "entities": [
      {
        "tableName": "analytics_event",
        "createSql": "CREATE TABLE IF NOT EXISTS `${TABLE_NAME}` (`name` TEXT NOT NULL, `paypal_context_id` TEXT, `link_type` TEXT, `timestamp` INTEGER NOT NULL, `venmo_installed` INTEGER NOT NULL DEFAULT 0, `is_vault` INTEGER NOT NULL DEFAULT 0, `start_time` INTEGER NOT NULL DEFAULT -1, `end_time` INTEGER NOT NULL DEFAULT -1, `endpoint` TEXT, `_id` INTEGER PRIMARY KEY AUTOINCREMENT NOT NULL)",
        "fields": [
          {
            "fieldPath": "name",
            "columnName": "name",
            "affinity": "TEXT",
            "notNull": true
          },
          {
            "fieldPath": "payPalContextId",
            "columnName": "paypal_context_id",
            "affinity": "TEXT",
            "notNull": false
          },
          {
            "fieldPath": "linkType",
            "columnName": "link_type",
            "affinity": "TEXT",
            "notNull": false
          },
          {
            "fieldPath": "timestamp",
            "columnName": "timestamp",
            "affinity": "INTEGER",
            "notNull": true
          },
          {
            "fieldPath": "venmoInstalled",
            "columnName": "venmo_installed",
            "affinity": "INTEGER",
            "notNull": true,
            "defaultValue": "0"
          },
          {
            "fieldPath": "isVaultRequest",
            "columnName": "is_vault",
            "affinity": "INTEGER",
            "notNull": true,
            "defaultValue": "0"
          },
          {
            "fieldPath": "startTime",
            "columnName": "start_time",
            "affinity": "INTEGER",
            "notNull": true,
            "defaultValue": "-1"
          },
          {
            "fieldPath": "endTime",
            "columnName": "end_time",
            "affinity": "INTEGER",
            "notNull": true,
            "defaultValue": "-1"
          },
          {
            "fieldPath": "endpoint",
            "columnName": "endpoint",
            "affinity": "TEXT",
            "notNull": false
          },
          {
            "fieldPath": "id",
            "columnName": "_id",
            "affinity": "INTEGER",
            "notNull": true
          }
        ],
        "primaryKey": {
          "columnNames": [
            "_id"
          ],
          "autoGenerate": true
        },
        "indices": [],
        "foreignKeys": []
      }
    ],
    "views": [],
    "setupQueries": [
      "CREATE TABLE IF NOT EXISTS room_master_table (id INTEGER PRIMARY KEY,identity_hash TEXT)",
      "INSERT OR REPLACE INTO room_master_table (id,identity_hash) VALUES(42, '633f69f1d2070981b77055c034388dcf')"
    ]
  }
}