{
  "project_info": {
    "project_number": "666942794030",
    "project_id": "braintree-demo-app",
    "storage_bucket": "braintree-demo-app.appspot.com"
  },
  "client": [
    {
      "client_info": {
        "mobilesdk_app_id": "1:666942794030:android:7e6736fd42c55efc4472bf",
        "android_client_info": {
          "package_name": "com.braintreepayments.demo"
        }
      },
      "oauth_client": [],
      "api_key": [
        {
          "current_key": "AIzaSyCXoiOf33bOF67L8rPlvExrOijCN_DC43Y"
        }
      ],
      "services": {
        "appinvite_service": {
          "other_platform_oauth_client": []
        }
      }
    }
  ],
  "configuration_version": "1"
}